aiospider
tests
