Metadata-Version: 1.2
Name: aiospider
Version: 0.0.11
Summary: A spider use asyncio.
Home-page: UNKNOWN
Author: EINDEX
Author-email: hi@eindex.me
License: MIT License
Platform: any
Requires-Python: >=3.6
